Pxucz/__init__.py
Pxucz/__pycache__/__init__.cpython-310.pyc
Pxucz/benchmark/__init__.py
Pxucz/benchmark/graphics.py
Pxucz/benchmark/__pycache__/__init__.cpython-310.pyc
Pxucz/benchmark/__pycache__/graphics.cpython-310.pyc
Pxucz/graphics/__init__.py
Pxucz/graphics/allignment.py
Pxucz/graphics/image.py
Pxucz/graphics/texture.py
Pxucz/graphics/window.py
Pxucz/graphics/__pycache__/__init__.cpython-310.pyc
Pxucz/graphics/__pycache__/allignment.cpython-310.pyc
Pxucz/graphics/__pycache__/image.cpython-310.pyc
Pxucz/graphics/__pycache__/texture.cpython-310.pyc
Pxucz/graphics/__pycache__/window.cpython-310.pyc
Pxucz/initial/__init__.py
Pxucz/initial/init.py
Pxucz/initial/opener.py
Pxucz/initial/set_variables.py
Pxucz/initial/__pycache__/__init__.cpython-310.pyc
Pxucz/initial/__pycache__/init.cpython-310.pyc
Pxucz/initial/__pycache__/opener.cpython-310.pyc
Pxucz/initial/__pycache__/set_variables.cpython-310.pyc
Pxucz/input/KeyboardInput.py
Pxucz/input/__init__.py
Pxucz/input/__pycache__/KeyboardInput.cpython-310.pyc
Pxucz/input/__pycache__/__init__.cpython-310.pyc
Pxucz/utils/__init__.py
Pxucz/utils/build.py
Pxucz/utils/clear.py
Pxucz/utils/global_path.py
Pxucz/utils/global_variables.py
Pxucz/utils/__pycache__/__init__.cpython-310.pyc
Pxucz/utils/__pycache__/build.cpython-310.pyc
Pxucz/utils/__pycache__/clear.cpython-310.pyc
Pxucz/utils/__pycache__/global_path.cpython-310.pyc
Pxucz/utils/__pycache__/global_variables.cpython-310.pyc
Pxucz/utils/clear_m/__init__.py
Pxucz/utils/clear_m/prettier.py
Pxucz/utils/clear_m/requirements_txt.py
Pxucz-0.0.1.8.dist-info/LICENSE
Pxucz-0.0.1.8.dist-info/METADATA
Pxucz-0.0.1.8.dist-info/WHEEL
Pxucz-0.0.1.8.dist-info/top_level.txt
Pxucz-0.0.1.8.dist-info/RECORD
