Metadata-Version: 2.1
Name: Pxucz
Version: 0.0.1.8
Summary: 2D Game Engine
Home-page: https://github.com/Cshtarn/Pxucz
Author: Cshtarn
Author-email: cshtarn@gmail.com
License: UNKNOWN
Platform: UNKNOWN
Classifier: Programming Language :: Python :: 3
Classifier: License :: OSI Approved :: MIT License
Classifier: Operating System :: OS Independent
License-File: LICENSE
Requires-Dist: black (==22.6.0)
Requires-Dist: bleach (==5.0.1)
Requires-Dist: certifi (==2022.6.15)
Requires-Dist: charset-normalizer (==2.1.0)
Requires-Dist: click (==8.1.3)
Requires-Dist: colorama (==0.4.5)
Requires-Dist: commonmark (==0.9.1)
Requires-Dist: docutils (==0.19)
Requires-Dist: glfw (==2.5.4)
Requires-Dist: idna (==3.3)
Requires-Dist: importlib-metadata (==4.12.0)
Requires-Dist: keyboard (==0.13.5)
Requires-Dist: keyring (==23.8.2)
Requires-Dist: mypy-extensions (==0.4.3)
Requires-Dist: Nuitka (==1.0.3)
Requires-Dist: numpy (==1.23.1)
Requires-Dist: ordered-set (==4.1.0)
Requires-Dist: pathspec (==0.9.0)
Requires-Dist: Pillow (==9.2.0)
Requires-Dist: pkginfo (==1.8.3)
Requires-Dist: platformdirs (==2.5.2)
Requires-Dist: Pxucz (==0.0.1.7)
Requires-Dist: PyAudio (==0.2.12)
Requires-Dist: Pygments (==2.12.0)
Requires-Dist: PyOpenGL (==3.1.6)
Requires-Dist: PyOpenGL-accelerate (==3.1.6)
Requires-Dist: PySide6 (==6.3.1)
Requires-Dist: PySide6-Addons (==6.3.1)
Requires-Dist: PySide6-Essentials (==6.3.1)
Requires-Dist: pywin32-ctypes (==0.2.0)
Requires-Dist: readme-renderer (==36.0)
Requires-Dist: requests (==2.28.1)
Requires-Dist: requests-toolbelt (==0.9.1)
Requires-Dist: rfc3986 (==2.0.0)
Requires-Dist: rich (==12.5.1)
Requires-Dist: shiboken6 (==6.3.1)
Requires-Dist: six (==1.16.0)
Requires-Dist: tomli (==2.0.1)
Requires-Dist: twine (==4.0.1)
Requires-Dist: urllib3 (==1.26.11)
Requires-Dist: webencodings (==0.5.1)
Requires-Dist: zipp (==3.8.1)
